{
	"name": "olio.sd.config",
	"ioConstraints": [
		"unknown"
	],
	"fields": [
		{
			"name": "description",
			"type": "string" 
		},
		{
			"name": "imageAction",
			"type": "string",
			"description": "Verb phrase describing the action to be performed in the image." 
		},
		{
			"name": "seed",
			"type": "int",
			"default": -1 
		},
		{
			"name": "hires",
			"type": "boolean",
			"default": true,
			"description": "Whether to use the refiner."
		},
		{
			"name": "steps",
			"type": "int",
			"minValue": 1,
			"maxValue": 100,
			"default": 20	
		},
		{
			"name": "refinerSteps",
			"type": "int",
			"minValue": 1,
			"maxValue": 100,
			"default": 20	
		},
		{
			"name": "width",
			"type": "int",
			"minValue": 1,
			"maxValue": 2048,
			"default": 1024
		},
		{
			"name": "height",
			"type": "int",
			"minValue": 1,
			"maxValue": 2048,
			"default": 1024
		},
		{
			"name": "cfg",
			"type": "int",
			"minValue": 1,
			"maxValue": 20,
			"default": 7	
		},
		{
			"name": "model",
			"type": "string"
		},
		{
			"name": "scheduler",
			"type": "string",
			"default": "Karras"
		},
		{
			"name": "sampler",
			"type": "string",
			"default": "dpm_2"
		},
		{
			"name": "refinerScheduler",
			"type": "string",
			"default": "Karras"
		},
		{
			"name": "refinerSampler",
			"type": "string",
			"default": "dpm_2"
		},
		{
			"name": "refinerModel",
			"type": "string"
		},
		{
			"name": "refinerMethod",
			"type": "string",
			"default": "PostApply"
		},
		{
			"name": "refinerUpscaleMethod",
			"type": "string",
			"default": "pixel-lanczos"
		},
		{
			"name": "refinerControlPercentage",
			"type": "double",
			"minValue": 0.01,
			"maxValue": 1.0,
			"default": 0.7
		},
		{
			"name": "refinerUpscale",
			"type": "int",
			"minValue": 1,
			"maxValue": 2,
			"default": 2
		},
		{
			"name": "refinerCfg",
			"type": "int",
			"minValue": 1,
			"maxValue": 20,
			"default": 7	
		},
		{
			"name": "imageCount",
			"type": "int",
			"default": 1,
			"minValue": 1,
			"maxValue": 5
		},
		{
			"name": "imageSetting",
			"type": "string",
			"default": "random"
		},
		{
			"name": "bodyStyle",
			"type": "string",
			"default": "full body"
		},
		{
			"name": "stillCamera",
			"type": "string"
		},
		{
			"name": "film",
			"type": "string"
		},
		{
			"name": "lens",
			"type": "string"
		},
		{
			"name": "colorProcess",
			"type": "string"
		},
		{
			"name": "photographer",
			"type": "string"
		},
		{
			"name": "movieCamera",
			"type": "string"
		},
		{
			"name": "movieFilm",
			"type": "string"
		},
		{
			"name": "director",
			"type": "string"
		},
		{
			"name": "photoStyle",
			"type": "string"
		},
		{
			"name": "style",
			"type": "string",
			"limit": ["art", "movie", "photograph"]
		},
		{
			"name": "artStyle",
			"type": "string"
		}
	]
}